dcmstack/__init__.py
dcmstack/dcmmeta.py
dcmstack/dcmstack.py
dcmstack/dcmstack_cli.py
dcmstack/extract.py
dcmstack/info.py
dcmstack/nitool_cli.py
dcmstack/utils.py
dcmstack-0.9.0.dist-info/COPYING
dcmstack-0.9.0.dist-info/METADATA
dcmstack-0.9.0.dist-info/WHEEL
dcmstack-0.9.0.dist-info/entry_points.txt
dcmstack-0.9.0.dist-info/top_level.txt
dcmstack-0.9.0.dist-info/RECORD
