Metadata-Version: 2.1
Name: dcmstack
Version: 0.9.0
Summary: Stack DICOM images into volumes and convert to Nifti
Home-page: https://github.com/moloney/dcmstack
Author: Brendan Moloney
Author-email: moloney@ohsu.edu
Maintainer: Brendan Moloney
Maintainer-email: moloney@ohsu.edu
Platform: OS Independent
Classifier: Development Status :: 3 - Alpha
Classifier: Environment :: Console
Classifier: Intended Audience :: Science/Research
Classifier: License :: OSI Approved :: MIT License
Classifier: Operating System :: OS Independent
Classifier: Programming Language :: Python
Classifier: Topic :: Scientific/Engineering
Provides: dcmstack
Requires-Python: >=2.7
License-File: COPYING
Requires-Dist: pydicom (>=0.9.7)
Requires-Dist: nibabel (>=2.5.1)
Requires-Dist: pylibjpeg-libjpeg ; python_version >= "3.7"
Provides-Extra: doc
Requires-Dist: sphinx ; extra == 'doc'
Requires-Dist: numpydoc ; extra == 'doc'
Provides-Extra: test
Requires-Dist: pytest-cov ; extra == 'test'
Requires-Dist: pytest (<=4.6) ; (python_version == "2.7") and extra == 'test'
Requires-Dist: pytest ; (python_version > "2.7") and extra == 'test'
